<?xml version="1.0" encoding="UTF-8"?>
<!DOCTYPE mapper PUBLIC "-//mybatis.org//DTD Mapper 3.0//EN" "http://mybatis.org/dtd/mybatis-3-mapper.dtd">
<mapper namespace="com.mama100.lotteryweb.mapper.BwGoodtipsMapper">
  <resultMap id="BaseResultMap" type="com.mama100.lotteryweb.po.BwGoodtips">
    <!--
      WARNING - @mbg.generated
      This element is automatically generated by MyBatis Generator, do not modify.
      This element was generated on Tue Jan 11 16:35:30 CST 2022.
    -->
    <id column="tip_id" jdbcType="BIGINT" property="tipId" />
    <result column="activity_id" jdbcType="BIGINT" property="activityId" />
    <result column="big_tips" jdbcType="VARCHAR" property="bigTips" />
    <result column="small_tips" jdbcType="VARCHAR" property="smallTips" />
    <result column="updated_by" jdbcType="VARCHAR" property="updatedBy" />
  </resultMap>
  <sql id="Example_Where_Clause">
    <!--
      WARNING - @mbg.generated
      This element is automatically generated by MyBatis Generator, do not modify.
      This element was generated on Tue Jan 11 16:35:30 CST 2022.
    -->
    <where>
      <foreach collection="oredCriteria" item="criteria" separator="or">
        <if test="criteria.valid">
          <trim prefix="(" prefixOverrides="and" suffix=")">
            <foreach collection="criteria.criteria" item="criterion">
              <choose>
                <when test="criterion.noValue">
                  and ${criterion.condition}
                </when>
                <when test="criterion.singleValue">
                  and ${criterion.condition} #{criterion.value}
                </when>
                <when test="criterion.betweenValue">
                  and ${criterion.condition} #{criterion.value} and #{criterion.secondValue}
                </when>
                <when test="criterion.listValue">
                  and ${criterion.condition}
                  <foreach close=")" collection="criterion.value" item="listItem" open="(" separator=",">
                    #{listItem}
                  </foreach>
                </when>
              </choose>
            </foreach>
          </trim>
        </if>
      </foreach>
    </where>
  </sql>
  <sql id="Update_By_Example_Where_Clause">
    <!--
      WARNING - @mbg.generated
      This element is automatically generated by MyBatis Generator, do not modify.
      This element was generated on Tue Jan 11 16:35:30 CST 2022.
    -->
    <where>
      <foreach collection="example.oredCriteria" item="criteria" separator="or">
        <if test="criteria.valid">
          <trim prefix="(" prefixOverrides="and" suffix=")">
            <foreach collection="criteria.criteria" item="criterion">
              <choose>
                <when test="criterion.noValue">
                  and ${criterion.condition}
                </when>
                <when test="criterion.singleValue">
                  and ${criterion.condition} #{criterion.value}
                </when>
                <when test="criterion.betweenValue">
                  and ${criterion.condition} #{criterion.value} and #{criterion.secondValue}
                </when>
                <when test="criterion.listValue">
                  and ${criterion.condition}
                  <foreach close=")" collection="criterion.value" item="listItem" open="(" separator=",">
                    #{listItem}
                  </foreach>
                </when>
              </choose>
            </foreach>
          </trim>
        </if>
      </foreach>
    </where>
  </sql>
  <sql id="Base_Column_List">
    <!--
      WARNING - @mbg.generated
      This element is automatically generated by MyBatis Generator, do not modify.
      This element was generated on Tue Jan 11 16:35:30 CST 2022.
    -->
    tip_id, activity_id, big_tips, small_tips, updated_by
  </sql>
  <select id="selectByExample" parameterType="com.mama100.lotteryweb.po.BwGoodtipsExample" resultMap="BaseResultMap">
    <!--
      WARNING - @mbg.generated
      This element is automatically generated by MyBatis Generator, do not modify.
      This element was generated on Tue Jan 11 16:35:30 CST 2022.
    -->
    select
    <if test="distinct">
      distinct
    </if>
    <include refid="Base_Column_List" />
    from bw_goodTips
    <if test="_parameter != null">
      <include refid="Example_Where_Clause" />
    </if>
    <if test="orderByClause != null">
      order by ${orderByClause}
    </if>
  </select>
  <select id="selectByPrimaryKey" parameterType="java.lang.Long" resultMap="BaseResultMap">
    <!--
      WARNING - @mbg.generated
      This element is automatically generated by MyBatis Generator, do not modify.
      This element was generated on Tue Jan 11 16:35:30 CST 2022.
    -->
    select 
    <include refid="Base_Column_List" />
    from bw_goodTips
    where tip_id = #{tipId,jdbcType=BIGINT}
  </select>
  <delete id="deleteByPrimaryKey" parameterType="java.lang.Long">
    <!--
      WARNING - @mbg.generated
      This element is automatically generated by MyBatis Generator, do not modify.
      This element was generated on Tue Jan 11 16:35:30 CST 2022.
    -->
    delete from bw_goodTips
    where tip_id = #{tipId,jdbcType=BIGINT}
  </delete>
  <delete id="deleteByExample" parameterType="com.mama100.lotteryweb.po.BwGoodtipsExample">
    <!--
      WARNING - @mbg.generated
      This element is automatically generated by MyBatis Generator, do not modify.
      This element was generated on Tue Jan 11 16:35:30 CST 2022.
    -->
    delete from bw_goodTips
    <if test="_parameter != null">
      <include refid="Example_Where_Clause" />
    </if>
  </delete>
  <insert id="insert" parameterType="com.mama100.lotteryweb.po.BwGoodtips">
    <!--
      WARNING - @mbg.generated
      This element is automatically generated by MyBatis Generator, do not modify.
      This element was generated on Tue Jan 11 16:35:30 CST 2022.
    -->
    insert into bw_goodTips (tip_id, activity_id, big_tips, 
      small_tips, updated_by)
    values (#{tipId,jdbcType=BIGINT}, #{activityId,jdbcType=BIGINT}, #{bigTips,jdbcType=VARCHAR}, 
      #{smallTips,jdbcType=VARCHAR}, #{updatedBy,jdbcType=VARCHAR})
  </insert>
  <insert id="insertSelective" parameterType="com.mama100.lotteryweb.po.BwGoodtips">
    <!--
      WARNING - @mbg.generated
      This element is automatically generated by MyBatis Generator, do not modify.
      This element was generated on Tue Jan 11 16:35:30 CST 2022.
    -->
    insert into bw_goodTips
    <trim prefix="(" suffix=")" suffixOverrides=",">
      <if test="tipId != null">
        tip_id,
      </if>
      <if test="activityId != null">
        activity_id,
      </if>
      <if test="bigTips != null">
        big_tips,
      </if>
      <if test="smallTips != null">
        small_tips,
      </if>
      <if test="updatedBy != null">
        updated_by,
      </if>
    </trim>
    <trim prefix="values (" suffix=")" suffixOverrides=",">
      <if test="tipId != null">
        #{tipId,jdbcType=BIGINT},
      </if>
      <if test="activityId != null">
        #{activityId,jdbcType=BIGINT},
      </if>
      <if test="bigTips != null">
        #{bigTips,jdbcType=VARCHAR},
      </if>
      <if test="smallTips != null">
        #{smallTips,jdbcType=VARCHAR},
      </if>
      <if test="updatedBy != null">
        #{updatedBy,jdbcType=VARCHAR},
      </if>
    </trim>
  </insert>
  <select id="countByExample" parameterType="com.mama100.lotteryweb.po.BwGoodtipsExample" resultType="java.lang.Long">
    <!--
      WARNING - @mbg.generated
      This element is automatically generated by MyBatis Generator, do not modify.
      This element was generated on Tue Jan 11 16:35:30 CST 2022.
    -->
    select count(*) from bw_goodTips
    <if test="_parameter != null">
      <include refid="Example_Where_Clause" />
    </if>
  </select>
  <update id="updateByExampleSelective" parameterType="map">
    <!--
      WARNING - @mbg.generated
      This element is automatically generated by MyBatis Generator, do not modify.
      This element was generated on Tue Jan 11 16:35:30 CST 2022.
    -->
    update bw_goodTips
    <set>
      <if test="record.tipId != null">
        tip_id = #{record.tipId,jdbcType=BIGINT},
      </if>
      <if test="record.activityId != null">
        activity_id = #{record.activityId,jdbcType=BIGINT},
      </if>
      <if test="record.bigTips != null">
        big_tips = #{record.bigTips,jdbcType=VARCHAR},
      </if>
      <if test="record.smallTips != null">
        small_tips = #{record.smallTips,jdbcType=VARCHAR},
      </if>
      <if test="record.updatedBy != null">
        updated_by = #{record.updatedBy,jdbcType=VARCHAR},
      </if>
    </set>
    <if test="_parameter != null">
      <include refid="Update_By_Example_Where_Clause" />
    </if>
  </update>
  <update id="updateByExample" parameterType="map">
    <!--
      WARNING - @mbg.generated
      This element is automatically generated by MyBatis Generator, do not modify.
      This element was generated on Tue Jan 11 16:35:30 CST 2022.
    -->
    update bw_goodTips
    set tip_id = #{record.tipId,jdbcType=BIGINT},
      activity_id = #{record.activityId,jdbcType=BIGINT},
      big_tips = #{record.bigTips,jdbcType=VARCHAR},
      small_tips = #{record.smallTips,jdbcType=VARCHAR},
      updated_by = #{record.updatedBy,jdbcType=VARCHAR}
    <if test="_parameter != null">
      <include refid="Update_By_Example_Where_Clause" />
    </if>
  </update>
  <update id="updateByPrimaryKeySelective" parameterType="com.mama100.lotteryweb.po.BwGoodtips">
    <!--
      WARNING - @mbg.generated
      This element is automatically generated by MyBatis Generator, do not modify.
      This element was generated on Tue Jan 11 16:35:30 CST 2022.
    -->
    update bw_goodTips
    <set>
      <if test="activityId != null">
        activity_id = #{activityId,jdbcType=BIGINT},
      </if>
      <if test="bigTips != null">
        big_tips = #{bigTips,jdbcType=VARCHAR},
      </if>
      <if test="smallTips != null">
        small_tips = #{smallTips,jdbcType=VARCHAR},
      </if>
      <if test="updatedBy != null">
        updated_by = #{updatedBy,jdbcType=VARCHAR},
      </if>
    </set>
    where tip_id = #{tipId,jdbcType=BIGINT}
  </update>
  <update id="updateByPrimaryKey" parameterType="com.mama100.lotteryweb.po.BwGoodtips">
    <!--
      WARNING - @mbg.generated
      This element is automatically generated by MyBatis Generator, do not modify.
      This element was generated on Tue Jan 11 16:35:30 CST 2022.
    -->
    update bw_goodTips
    set activity_id = #{activityId,jdbcType=BIGINT},
      big_tips = #{bigTips,jdbcType=VARCHAR},
      small_tips = #{smallTips,jdbcType=VARCHAR},
      updated_by = #{updatedBy,jdbcType=VARCHAR}
    where tip_id = #{tipId,jdbcType=BIGINT}
  </update>
</mapper>